{
  "items": [
    {
      "tags": [
        "xubuntu"
      ],
      "owner": {
        "reputation": 68,
        "user_id": 2740907,
        "user_type": "registered",
        "profile_image": "https://www.gravatar.com/avatar/f91f766f00c0e1764e80228bc2daf859?s=128&d=identicon&r=PG",
        "display_name": "pajus_cz",
        "link": "http://stackoverflow.com/users/2740907/pajus-cz"
      },
      "is_answered": false,
      "view_count": 2,
      "answer_count": 1,
      "score": 0,
      "last_activity_date": 1416141987,
      "creation_date": 1416141968,
      "question_id": 26957053,
      "link": "http://stackoverflow.com/questions/26957053/xubuntu-14-04-how-to-use-two-keyboard-shortcuts-to-change-keyboard-layout",
      "title": "Xubuntu 14.04 How to use two keyboard shortcuts to change keyboard layout"
    },
    {
      "tags": [
        "php",
        "jquery",
        "ajax",
        "user-interface",
        "autocomplete"
      ],
      "owner": {
        "reputation": 1,
        "user_id": 4257916,
        "user_type": "registered",
        "profile_image": "https://www.gravatar.com/avatar/f2cdab7b51193a70615eab3f74e83e42?s=128&d=identicon&r=PG&f=1",
        "display_name": "Felix Klemm",
        "link": "http://stackoverflow.com/users/4257916/felix-klemm"
      },
      "is_answered": false,
      "view_count": 15,
      "answer_count": 2,
      "score": 0,
      "last_activity_date": 1416141974,
      "creation_date": 1416140558,
      "question_id": 26956852,
      "link": "http://stackoverflow.com/questions/26956852/error-syntax-error-unrecognized-expression-a-jquery-ui",
      "title": "Error: Syntax error, unrecognized expression: &lt;a/&gt; Jquery UI"
    },
    {
      "tags": [
        "c#"
      ],
      "owner": {
        "reputation": 1205,
        "user_id": 1424244,
        "user_type": "registered",
        "accept_rate": 72,
        "profile_image": "https://www.gravatar.com/avatar/d8d370542399af1afe3202ed1fc1ab88?s=128&d=identicon&r=PG",
        "display_name": "IllidanS4",
        "link": "http://stackoverflow.com/users/1424244/illidans4"
      },
      "is_answered": true,
      "view_count": 42,
      "answer_count": 3,
      "score": 1,
      "last_activity_date": 1416141967,
      "creation_date": 1416133939,
      "question_id": 26955976,
      "link": "http://stackoverflow.com/questions/26955976/compare-two-managed-references",
      "title": "Compare two managed references"
    },
    {
      "tags": [
        "javascript",
        "oop"
      ],
      "owner": {
        "reputation": 30,
        "user_id": 3335812,
        "user_type": "registered",
        "accept_rate": 50,
        "profile_image": "https://www.gravatar.com/avatar/f1d6f2e0174fd8c315c8b43838321095?s=128&d=identicon&r=PG&f=1",
        "display_name": "featherlight53",
        "link": "http://stackoverflow.com/users/3335812/featherlight53"
      },
      "is_answered": false,
      "view_count": 4,
      "answer_count": 0,
      "score": -1,
      "last_activity_date": 1416141966,
      "creation_date": 1416141966,
      "question_id": 26957052,
      "link": "http://stackoverflow.com/questions/26957052/what-are-some-good-applications-of-oojs",
      "title": "What are some good applications of OOJS?"
    },
    {
      "tags": [
        "c++",
        "const-correctness"
      ],
      "owner": {
        "reputation": 21,
        "user_id": 1235183,
        "user_type": "registered",
        "accept_rate": 25,
        "profile_image": "https://www.gravatar.com/avatar/59caaeef5801c8d3c82eb76080994599?s=128&d=identicon&r=PG",
        "display_name": "user1235183",
        "link": "http://stackoverflow.com/users/1235183/user1235183"
      },
      "is_answered": true,
      "view_count": 38,
      "answer_count": 2,
      "score": 2,
      "last_activity_date": 1416141965,
      "creation_date": 1416139592,
      "last_edit_date": 1416141158,
      "question_id": 26956733,
      "link": "http://stackoverflow.com/questions/26956733/passing-an-object-by-const-and-by-to-the-same-function",
      "title": "passing an object by const&amp; and by &amp; to the same function"
    },
    {
      "tags": [
        "java",
        "eclipse",
        "osx"
      ],
      "owner": {
        "reputation": 6,
        "user_id": 3051033,
        "user_type": "registered",
        "profile_image": "https://www.gravatar.com/avatar/e1d78b1389268d541125f83ae786ba27?s=128&d=identicon&r=PG&f=1",
        "display_name": "cabama",
        "link": "http://stackoverflow.com/users/3051033/cabama"
      },
      "is_answered": false,
      "view_count": 6,
      "answer_count": 0,
      "score": 1,
      "last_activity_date": 1416141960,
      "creation_date": 1416141392,
      "last_edit_date": 1416141960,
      "question_id": 26956970,
      "link": "http://stackoverflow.com/questions/26956970/java-gui-elements-with-black-background",
      "title": "Java GUI - Elements with Black Background"
    },
    {
      "tags": [
        "javascript",
        "html",
        "iframe",
        "fancybox"
      ],
      "owner": {
        "reputation": 3,
        "user_id": 3882974,
        "user_type": "registered",
        "profile_image": "https://www.gravatar.com/avatar/57a7bbacc514f9686e11c42bdee8fafc?s=128&d=identicon&r=PG&f=1",
        "display_name": "Chaosjosh",
        "link": "http://stackoverflow.com/users/3882974/chaosjosh"
      },
      "is_answered": false,
      "view_count": 2,
      "answer_count": 0,
      "score": 0,
      "last_activity_date": 1416141956,
      "creation_date": 1416141956,
      "question_id": 26957051,
      "link": "http://stackoverflow.com/questions/26957051/using-fancybox-to-bring-up-video-js-iframe-issue",
      "title": "Using Fancybox to bring up video-js iframe issue"
    },
    {
      "tags": [
        "android"
      ],
      "owner": {
        "reputation": 74,
        "user_id": 3954923,
        "user_type": "registered",
        "accept_rate": 74,
        "profile_image": "http://i.stack.imgur.com/adBGt.jpg?s=128&g=1",
        "display_name": "monkey coder",
        "link": "http://stackoverflow.com/users/3954923/monkey-coder"
      },
      "is_answered": true,
      "view_count": 29,
      "answer_count": 4,
      "score": 0,
      "last_activity_date": 1416141954,
      "creation_date": 1416116176,
      "question_id": 26954166,
      "link": "http://stackoverflow.com/questions/26954166/listactivity-not-working",
      "title": "ListActivity not working"
    },
    {
      "tags": [
        "c",
        "preprocessor",
        "c-preprocessor"
      ],
      "owner": {
        "reputation": 409,
        "user_id": 456065,
        "user_type": "registered",
        "accept_rate": 71,
        "profile_image": "https://www.gravatar.com/avatar/49b8a5172d9634e038c69110bfb5e480?s=128&d=identicon&r=PG",
        "display_name": "Sanich",
        "link": "http://stackoverflow.com/users/456065/sanich"
      },
      "is_answered": false,
      "view_count": 20,
      "answer_count": 1,
      "score": 1,
      "last_activity_date": 1416141950,
      "creation_date": 1416140213,
      "last_edit_date": 1416141721,
      "question_id": 26956810,
      "link": "http://stackoverflow.com/questions/26956810/error-c2003-expected-defined-id",
      "title": "error C2003: expected &#39;defined id&#39;"
    },
    {
      "tags": [
        "c",
        "sizeof"
      ],
      "owner": {
        "reputation": 10,
        "user_id": 3851486,
        "user_type": "registered",
        "accept_rate": 57,
        "profile_image": "https://www.gravatar.com/avatar/c9c831533d886455cca96bcab83414cc?s=128&d=identicon&r=PG&f=1",
        "display_name": "user3851486",
        "link": "http://stackoverflow.com/users/3851486/user3851486"
      },
      "is_answered": false,
      "view_count": 5,
      "answer_count": 0,
      "score": 0,
      "last_activity_date": 1416141947,
      "creation_date": 1416141947,
      "question_id": 26957049,
      "link": "http://stackoverflow.com/questions/26957049/return-value-of-sizeof-in-c",
      "title": "Return value of sizeof() in c?"
    },
    {
      "tags": [
        "google-api",
        "google-calendar",
        "jwt",
        "google-api-nodejs-client"
      ],
      "owner": {
        "reputation": 309,
        "user_id": 1418014,
        "user_type": "registered",
        "accept_rate": 62,
        "profile_image": "https://www.gravatar.com/avatar/cbde212986000125ff4322c25c1e50ce?s=128&d=identicon&r=PG",
        "display_name": "sil",
        "link": "http://stackoverflow.com/users/1418014/sil"
      },
      "is_answered": false,
      "view_count": 4,
      "answer_count": 0,
      "score": 0,
      "last_activity_date": 1416141947,
      "creation_date": 1416141947,
      "question_id": 26957048,
      "link": "http://stackoverflow.com/questions/26957048/google-calendar-api-service-token-only-has-reader-accessrole",
      "title": "Google Calendar API service token only has reader accessRole"
    },
    {
      "tags": [
        "java",
        "intellij-idea",
        "checkstyle"
      ],
      "owner": {
        "reputation": 85,
        "user_id": 4086747,
        "user_type": "registered",
        "accept_rate": 100,
        "profile_image": "http://graph.facebook.com/100000172437774/picture?type=large",
        "display_name": "Maxim Gotovchits",
        "link": "http://stackoverflow.com/users/4086747/maxim-gotovchits"
      },
      "is_answered": false,
      "view_count": 18,
      "answer_count": 1,
      "score": 1,
      "last_activity_date": 1416141931,
      "creation_date": 1416132132,
      "last_edit_date": 1416132864,
      "question_id": 26955766,
      "link": "http://stackoverflow.com/questions/26955766/intellij-idea-checkstyle",
      "title": "Intellij IDEA checkstyle"
    },
    {
      "tags": [
        "android",
        "pointers",
        "table",
        "data",
        "parse.com"
      ],
      "owner": {
        "reputation": 77,
        "user_id": 2185295,
        "user_type": "registered",
        "accept_rate": 50,
        "profile_image": "https://www.gravatar.com/avatar/37c6cbf41737925c159ed8b95cac7dd3?s=128&d=identicon&r=PG",
        "display_name": "muhammad usman khan",
        "link": "http://stackoverflow.com/users/2185295/muhammad-usman-khan"
      },
      "is_answered": false,
      "view_count": 11,
      "answer_count": 0,
      "score": 1,
      "last_activity_date": 1416141929,
      "creation_date": 1416129699,
      "last_edit_date": 1416141929,
      "question_id": 26955470,
      "link": "http://stackoverflow.com/questions/26955470/data-getting-from-table-using-parse-com-android",
      "title": "Data getting from table using parse.com android"
    },
    {
      "tags": [
        "web-applications",
        "intellij-idea",
        "jboss"
      ],
      "owner": {
        "reputation": 271,
        "user_id": 2322920,
        "user_type": "registered",
        "accept_rate": 90,
        "profile_image": "https://www.gravatar.com/avatar/e8e846dbc8813909dfa91b1ac39121cc?s=128&d=identicon&r=PG&f=1",
        "display_name": "Robin Hellemans",
        "link": "http://stackoverflow.com/users/2322920/robin-hellemans"
      },
      "is_answered": false,
      "view_count": 8,
      "answer_count": 1,
      "score": 0,
      "last_activity_date": 1416141924,
      "creation_date": 1416075667,
      "last_edit_date": 1416092125,
      "question_id": 26949149,
      "link": "http://stackoverflow.com/questions/26949149/unable-to-start-jboss-filenotfoundexception",
      "title": "Unable to start JBoss, Filenotfoundexception"
    },
    {
      "tags": [
        "regex",
        "perl"
      ],
      "owner": {
        "reputation": 1,
        "user_id": 4257954,
        "user_type": "registered",
        "profile_image": "https://www.gravatar.com/avatar/7bff583602b4c002a4d2edb5570d42a6?s=128&d=identicon&r=PG&f=1",
        "display_name": "Anu",
        "link": "http://stackoverflow.com/users/4257954/anu"
      },
      "is_answered": false,
      "view_count": 3,
      "answer_count": 0,
      "score": 0,
      "last_activity_date": 1416141921,
      "creation_date": 1416141921,
      "question_id": 26957045,
      "link": "http://stackoverflow.com/questions/26957045/im-trying-to-grep-a-pattern-in-multiple-files-and-print-the-corresponding-match",
      "title": "I&#39;m trying to grep a pattern in multiple files and print the corresponding matching lines to different new files."
    },
    {
      "tags": [
        "gcc",
        "preprocessor"
      ],
      "owner": {
        "reputation": 3137,
        "user_id": 2036917,
        "user_type": "registered",
        "accept_rate": 88,
        "profile_image": "http://i.stack.imgur.com/xBapf.png?s=128&g=1",
        "display_name": "Udo Klein",
        "link": "http://stackoverflow.com/users/2036917/udo-klein"
      },
      "is_answered": false,
      "view_count": 2,
      "answer_count": 0,
      "score": 0,
      "last_activity_date": 1416141906,
      "creation_date": 1416141906,
      "question_id": 26957044,
      "link": "http://stackoverflow.com/questions/26957044/macro-for-coroutines",
      "title": "Macro for coroutines"
    },
    {
      "tags": [
        "php",
        "codeigniter",
        "session"
      ],
      "owner": {
        "reputation": 3,
        "user_id": 4255581,
        "user_type": "registered",
        "profile_image": "https://www.gravatar.com/avatar/8c336db705b528094fd8a73ec0e0204c?s=128&d=identicon&r=PG&f=1",
        "display_name": "Danil",
        "link": "http://stackoverflow.com/users/4255581/danil"
      },
      "is_answered": false,
      "view_count": 8,
      "answer_count": 1,
      "score": 0,
      "last_activity_date": 1416141897,
      "creation_date": 1416141318,
      "question_id": 26956963,
      "link": "http://stackoverflow.com/questions/26956963/why-session-is-false-in-codeigniter",
      "title": "Why session is false in Codeigniter?"
    },
    {
      "tags": [
        "php",
        "mysql",
        "sql",
        "pivot",
        "multilanguage"
      ],
      "owner": {
        "reputation": 11,
        "user_id": 1908163,
        "user_type": "registered",
        "profile_image": "https://www.gravatar.com/avatar/16f81374dac522e2816a5f444cb0bf45?s=128&d=identicon&r=PG",
        "display_name": "Jean",
        "link": "http://stackoverflow.com/users/1908163/jean"
      },
      "is_answered": true,
      "view_count": 77,
      "bounty_amount": 150,
      "bounty_closes_date": 1416691443,
      "answer_count": 3,
      "score": 2,
      "last_activity_date": 1416141893,
      "creation_date": 1404818811,
      "last_edit_date": 1416088312,
      "question_id": 24630613,
      "link": "http://stackoverflow.com/questions/24630613/mysql-grab-value-from-different-row-and-return-them-on-the-same-row",
      "title": "MYSQL - Grab value from different row and return them on the same row"
    },
    {
      "tags": [
        "c++",
        "mysql",
        "mingw",
        "windows-7-x64",
        "connector"
      ],
      "owner": {
        "reputation": 1,
        "user_id": 4012388,
        "user_type": "registered",
        "profile_image": "https://www.gravatar.com/avatar/19d17441e1d73c7f80c3cf98628a4ba0?s=128&d=identicon&r=PG&f=1",
        "display_name": "Sunil Verma",
        "link": "http://stackoverflow.com/users/4012388/sunil-verma"
      },
      "is_answered": false,
      "view_count": 2,
      "answer_count": 0,
      "score": 0,
      "last_activity_date": 1416141887,
      "creation_date": 1416141887,
      "question_id": 26957041,
      "link": "http://stackoverflow.com/questions/26957041/mingw-mysql-c-connector-crashes-on-driver-connect",
      "title": "mingw mysql c++ connector crashes on driver connect"
    },
    {
      "tags": [
        "python",
        "go"
      ],
      "owner": {
        "reputation": 675,
        "user_id": 1297203,
        "user_type": "registered",
        "accept_rate": 56,
        "profile_image": "https://www.gravatar.com/avatar/b213707b2fdedeacf904335b540f1e8f?s=128&d=identicon&r=PG",
        "display_name": "holys",
        "link": "http://stackoverflow.com/users/1297203/holys"
      },
      "is_answered": false,
      "view_count": 8,
      "answer_count": 0,
      "score": -1,
      "last_activity_date": 1416141886,
      "creation_date": 1416141886,
      "question_id": 26957040,
      "link": "http://stackoverflow.com/questions/26957040/how-to-implement-the-python-zip-function-in-golang",
      "title": "how to implement the python `zip` function in golang?"
    },
    {
      "tags": [
        "c#",
        "ios",
        "wpf",
        "button",
        "shader"
      ],
      "owner": {
        "reputation": 11,
        "user_id": 3767987,
        "user_type": "registered",
        "profile_image": "http://i.stack.imgur.com/d7DMG.jpg?s=128&g=1",
        "display_name": "user3767987",
        "link": "http://stackoverflow.com/users/3767987/user3767987"
      },
      "is_answered": false,
      "view_count": 4,
      "answer_count": 0,
      "score": 0,
      "last_activity_date": 1416141883,
      "creation_date": 1416141883,
      "question_id": 26957039,
      "link": "http://stackoverflow.com/questions/26957039/wpf-creating-ios-passcode-buttons",
      "title": "WPF creating ios passcode buttons"
    },
    {
      "tags": [
        "java",
        "android",
        "eclipse",
        "manifest",
        "instagram"
      ],
      "owner": {
        "reputation": 1,
        "user_id": 4257772,
        "user_type": "registered",
        "profile_image": "https://www.gravatar.com/avatar/2336847364ce7399a28ad3a84793fa0b?s=128&d=identicon&r=PG&f=1",
        "display_name": "Samia",
        "link": "http://stackoverflow.com/users/4257772/samia"
      },
      "is_answered": false,
      "view_count": 5,
      "answer_count": 0,
      "score": -1,
      "last_activity_date": 1416141871,
      "creation_date": 1416141871,
      "question_id": 26957038,
      "link": "http://stackoverflow.com/questions/26957038/instagram-is-not-working",
      "title": "Instagram is not working"
    },
    {
      "tags": [
        "android",
        "json"
      ],
      "owner": {
        "reputation": 1,
        "user_id": 3942959,
        "user_type": "registered",
        "profile_image": "https://www.gravatar.com/avatar/013c82b7d4e2cb7855d18543493d8519?s=128&d=identicon&r=PG&f=1",
        "display_name": "Raddix",
        "link": "http://stackoverflow.com/users/3942959/raddix"
      },
      "is_answered": false,
      "view_count": 6,
      "answer_count": 1,
      "score": 0,
      "last_activity_date": 1416141863,
      "creation_date": 1416141400,
      "question_id": 26956971,
      "link": "http://stackoverflow.com/questions/26956971/how-to-tell-the-if-the-city-is-incorrect-in-openweathermap-api-and-in-android",
      "title": "How to tell the if the City is incorrect in OpenWeatherMap api and in android"
    },
    {
      "tags": [
        "cordova",
        "admob",
        "phonegap-plugins"
      ],
      "owner": {
        "reputation": 86,
        "user_id": 2953593,
        "user_type": "registered",
        "accept_rate": 52,
        "profile_image": "https://www.gravatar.com/avatar/3a05a71ae7145c63e1a90325f8258185?s=128&d=identicon&r=PG&f=1",
        "display_name": "Bacon2305",
        "link": "http://stackoverflow.com/users/2953593/bacon2305"
      },
      "is_answered": true,
      "view_count": 2238,
      "accepted_answer_id": 22002857,
      "answer_count": 3,
      "score": 1,
      "last_activity_date": 1416141855,
      "creation_date": 1393290129,
      "last_edit_date": 1395950250,
      "question_id": 22002524,
      "link": "http://stackoverflow.com/questions/22002524/admob-or-ad-plugin-for-android-available-for-cordova-phonegap-3-3",
      "title": "Admob or Ad plugin for Android available for Cordova/Phonegap 3.3?"
    },
    {
      "tags": [
        "c",
        "caching",
        "cpu"
      ],
      "owner": {
        "reputation": 420,
        "user_id": 1791534,
        "user_type": "registered",
        "accept_rate": 88,
        "profile_image": "https://www.gravatar.com/avatar/4c8551210c2992777f91586f6edabad9?s=128&d=identicon&r=PG",
        "display_name": "Larry",
        "link": "http://stackoverflow.com/users/1791534/larry"
      },
      "is_answered": false,
      "view_count": 3,
      "answer_count": 0,
      "score": 0,
      "last_activity_date": 1416141852,
      "creation_date": 1416141852,
      "question_id": 26957035,
      "link": "http://stackoverflow.com/questions/26957035/c-cpu-cache-associativity-theory-and-practice-confusion",
      "title": "c - cpu cache associativity - theory and practice confusion"
    },
    {
      "tags": [
        "algorithm",
        "solver"
      ],
      "owner": {
        "reputation": 58,
        "user_id": 2227449,
        "user_type": "registered",
        "accept_rate": 50,
        "profile_image": "https://www.gravatar.com/avatar/5f86dcbcf32d448f2794504242d49506?s=128&d=identicon&r=PG",
        "display_name": "Mah Kh",
        "link": "http://stackoverflow.com/users/2227449/mah-kh"
      },
      "is_answered": false,
      "view_count": 14,
      "answer_count": 1,
      "score": 0,
      "last_activity_date": 1416141838,
      "creation_date": 1416135649,
      "question_id": 26956205,
      "link": "http://stackoverflow.com/questions/26956205/solvability-of-a-version-of-lights-out-game",
      "title": "solvability of a version of lights out game"
    },
    {
      "tags": [
        "ios",
        "objective-c",
        "xcode"
      ],
      "owner": {
        "reputation": 146,
        "user_id": 2373410,
        "user_type": "registered",
        "accept_rate": 44,
        "profile_image": "https://www.gravatar.com/avatar/684a479ecdc16beb9c6ddd01073f2fee?s=128&d=identicon&r=PG",
        "display_name": "Pangu",
        "link": "http://stackoverflow.com/users/2373410/pangu"
      },
      "is_answered": false,
      "view_count": 4,
      "answer_count": 0,
      "score": 0,
      "last_activity_date": 1416141838,
      "creation_date": 1416141838,
      "question_id": 26957033,
      "link": "http://stackoverflow.com/questions/26957033/how-do-i-change-a-uibutton-label-text-when-a-menu-slides-up-or-down",
      "title": "How do I change a UIButton label text when a menu slides up or down?"
    },
    {
      "tags": [
        "haskell",
        "data-structures",
        "multidimensional-array",
        "contingency"
      ],
      "owner": {
        "reputation": 600,
        "user_id": 700023,
        "user_type": "registered",
        "accept_rate": 70,
        "profile_image": "https://www.gravatar.com/avatar/e2f5fba9211d2456ec9eae6550bdb1af?s=128&d=identicon&r=PG",
        "display_name": "fstab",
        "link": "http://stackoverflow.com/users/700023/fstab"
      },
      "is_answered": false,
      "view_count": 3,
      "answer_count": 0,
      "score": 0,
      "last_activity_date": 1416141838,
      "creation_date": 1416141838,
      "question_id": 26957032,
      "link": "http://stackoverflow.com/questions/26957032/how-to-represent-a-numerical-table-for-example-a-contingency-table-in-haskell",
      "title": "How to represent a numerical table (for example a contingency table) in Haskell?"
    },
    {
      "tags": [
        "c#",
        "asp.net",
        "asp.net-web-api",
        "mono"
      ],
      "owner": {
        "reputation": 447,
        "user_id": 3022229,
        "user_type": "registered",
        "accept_rate": 69,
        "profile_image": "https://www.gravatar.com/avatar/483b1f0eb6d5a8fd4100088cb2530e6e?s=128&d=identicon&r=PG",
        "display_name": "Jerry Bian",
        "link": "http://stackoverflow.com/users/3022229/jerry-bian"
      },
      "is_answered": true,
      "view_count": 534,
      "accepted_answer_id": 24232036,
      "answer_count": 2,
      "score": 1,
      "last_activity_date": 1416141834,
      "creation_date": 1402678597,
      "question_id": 24210346,
      "link": "http://stackoverflow.com/questions/24210346/could-not-load-type-system-web-http-webhost-routing-httprouteexceptionhandler",
      "title": "Could not load type &#39;System.Web.Http.WebHost.Routing.HttpRouteExceptionHandler&#39; in Mono"
    },
    {
      "tags": [
        "regex",
        "linux",
        "bash",
        "sed",
        "substring"
      ],
      "owner": {
        "reputation": 1,
        "user_id": 3986322,
        "user_type": "registered",
        "profile_image": "https://www.gravatar.com/avatar/3170e9b52689128eb906890a559f84ec?s=128&d=identicon&r=PG&f=1",
        "display_name": "Matthew",
        "link": "http://stackoverflow.com/users/3986322/matthew"
      },
      "is_answered": true,
      "view_count": 25,
      "answer_count": 2,
      "score": 0,
      "last_activity_date": 1416141834,
      "creation_date": 1416140707,
      "last_edit_date": 1416141044,
      "question_id": 26956870,
      "link": "http://stackoverflow.com/questions/26956870/finding-all-phone-numbers",
      "title": "Finding all phone numbers"
    }
  ],
  "has_more": true,
  "quota_max": 10000,
  "quota_remaining": 9991
}